LICENSE
README.md
setup.py
nano_profiler/__init__.py
nano_profiler/nano_profiler.py
nano_profiler.egg-info/PKG-INFO
nano_profiler.egg-info/SOURCES.txt
nano_profiler.egg-info/dependency_links.txt
nano_profiler.egg-info/top_level.txt